{"skeleton":{"hash":"n9jAvBs7LR53yraloSUkVS5xYgI","spine":"2.1.27","width":255.37,"height":289.29,"images":""},"bones":[{"name":"root"},{"name":"bone","parent":"root"},{"name":"bone2","parent":"root","x":96},{"name":"bone3","parent":"root","x":96,"y":57.43},{"name":"bone4","parent":"root","x":96,"y":110.07},{"name":"bone5","parent":"root","x":96,"y":161.29}],"slots":[{"name":"bingkuai_0","bone":"bone","attachment":"bingkuai_0","blend":"screen"},{"name":"xingxing_0","bone":"bone2","attachment":"xingxing_0","blend":"screen"},{"name":"xingxing_1","bone":"bone3","attachment":"xingxing_0","blend":"screen"},{"name":"xingxing_2","bone":"bone4","attachment":"xingxing_0","blend":"screen"},{"name":"xingxing_3","bone":"bone5","attachment":"xingxing_0","blend":"screen"}],"skins":{"default":{"bingkuai_0":{"bingkuai_0":{"x":4.62,"y":69.38,"width":200,"height":200}},"xingxing_0":{"xingxing_0":{"width":128,"height":128}},"xingxing_1":{"xingxing_0":{"width":128,"height":128}},"xingxing_2":{"xingxing_0":{"width":128,"height":128}},"xingxing_3":{"xingxing_0":{"width":128,"height":128}}}},"animations":{"animation":{"slots":{"xingxing_0":{"color":[{"time":0,"color":"ffffff00"},{"time":0.2666,"color":"ffffffff"},{"time":0.5333,"color":"ffffff00","curve":"stepped"},{"time":1.8,"color":"ffffff00"},{"time":2.0666,"color":"ffffffff"},{"time":2.3333,"color":"ffffff00"}]},"xingxing_1":{"color":[{"time":0,"color":"ffffff00","curve":"stepped"},{"time":0.2666,"color":"ffffff00"},{"time":0.5,"color":"ffffffff"},{"time":0.7333,"color":"ffffff00","curve":"stepped"},{"time":2.3333,"color":"ffffff00"},{"time":2.7333,"color":"ffffffff"},{"time":3.1,"color":"ffffff00"}]},"xingxing_2":{"color":[{"time":0,"color":"ffffff00","curve":"stepped"},{"time":0.4666,"color":"ffffff00"},{"time":0.7333,"color":"ffffffff"},{"time":1,"color":"ffffff00"}]},"xingxing_3":{"color":[{"time":0,"color":"ffffff00","curve":"stepped"},{"time":1.2,"color":"ffffff00"},{"time":1.5,"color":"ffffffff"},{"time":1.8333,"color":"ffffff00"}]}},"bones":{"bone":{"scale":[{"time":0,"x":1.5,"y":1.5}]},"bone2":{"rotate":[{"time":0,"angle":0},{"time":0.5333,"angle":-90,"curve":"stepped"},{"time":1.8,"angle":-90},{"time":1.8333,"angle":0},{"time":2.3333,"angle":-90}],"translate":[{"time":0,"x":-138.95,"y":124.1,"curve":"stepped"},{"time":1.8,"x":-138.95,"y":124.1},{"time":1.8333,"x":-130.66,"y":98.4}],"scale":[{"time":0,"x":0.8,"y":0.8,"curve":"stepped"},{"time":1.8,"x":0.8,"y":0.8},{"time":1.8333,"x":0.7,"y":0.7}]},"bone3":{"rotate":[{"time":0,"angle":0},{"time":0.7333,"angle":-120,"curve":"stepped"},{"time":2.3333,"angle":-120},{"time":2.3666,"angle":0},{"time":3.1,"angle":-90}],"translate":[{"time":0,"x":-39.44,"y":81.65,"curve":"stepped"},{"time":2.3333,"x":-39.44,"y":81.65},{"time":2.3666,"x":-57.58,"y":-13.35}],"scale":[{"time":0,"x":0.5,"y":0.5,"curve":"stepped"},{"time":2.3333,"x":0.5,"y":0.5},{"time":2.3666,"x":0.7,"y":0.7}]},"bone4":{"rotate":[{"time":0,"angle":0,"curve":"stepped"},{"time":0.4666,"angle":0},{"time":1,"angle":-100}],"translate":[{"time":0,"x":-104.58,"y":-72.27}],"scale":[{"time":0,"x":0.7,"y":0.7}]},"bone5":{"rotate":[{"time":0,"angle":0,"curve":"stepped"},{"time":1.2,"angle":0},{"time":1.8333,"angle":-90}],"translate":[{"time":0,"x":-66.97,"y":23.63}],"scale":[{"time":0,"x":0.75,"y":0.75}]}}}}}